sortdicom/__init__.py
sortdicom/sortdicom.py
sortdicom/tests/test_main.py
sortdicom-0.5.0.dist-info/entry_points.txt
sortdicom-0.5.0.dist-info/LICENSE
sortdicom-0.5.0.dist-info/METADATA
sortdicom-0.5.0.dist-info/WHEEL
sortdicom-0.5.0.dist-info/RECORD
