Metadata-Version: 2.1
Name: sortdicom
Version: 0.5.0
Summary: Sorts and Anonymises Dicoms
Home-page: https://github.com/sbu-physics-mri/sortdicom
Author: Alex Drysdale
Author-email: alexander.drysdale@wales.nhs.uk
Requires-Python: >=3.12,<4.0
Classifier: Programming Language :: Python :: 3
Classifier: Programming Language :: Python :: 3.12
Requires-Dist: pydicom (>=3.0.1,<4.0.0)
Project-URL: Repository, https://github.com/sbu-physics-mri/sortdicom
